trash_manager/__about__.py
trash_manager/__init__.py
trash_manager/config.py
trash_manager/trash_item.py
trash_manager/trash_manager.py
trash_manager-0.0.3.dist-info/METADATA
trash_manager-0.0.3.dist-info/WHEEL
trash_manager-0.0.3.dist-info/licenses/LICENSE.txt
trash_manager-0.0.3.dist-info/RECORD
